{
  "href": "https://api.spotify.com/v1/me/tracks?offset=650&limit=50&market=from_token",
  "items": [
    {
      "added_at": "2017-10-30T17:35:39Z",
      "track": {
        "album": {
          "album_type": "album",
          "artists": [
            {
              "external_urls": {
                "spotify": "https://open.spotify.com/artist/5M52tdBnJaKSvOpJGz8mfZ"
              },
              "href": "https://api.spotify.com/v1/artists/5M52tdBnJaKSvOpJGz8mfZ",
              "id": "5M52tdBnJaKSvOpJGz8mfZ",
              "name": "Black Sabbath",
              "type": "artist",
              "uri": "spotify:artist:5M52tdBnJaKSvOpJGz8mfZ"
            }
          ],
          "external_urls": {
            "spotify": "https://open.spotify.com/album/3iRW4cZOM90lX9Rtc2Qglh"
          },
          "href": "https://api.spotify.com/v1/albums/3iRW4cZOM90lX9Rtc2Qglh",
          "id": "3iRW4cZOM90lX9Rtc2Qglh",
          "images": [
            {
              "height": 640,
              "url": "https://i.scdn.co/image/6fece4e967304bcecaac8acf434227c2a7c13e31",
              "width": 640
            },
            {
              "height": 300,
              "url": "https://i.scdn.co/image/5805ee36907961fa1d1e46a2f5653ea892b1b9ad",
              "width": 300
            },
            {
              "height": 64,
              "url": "https://i.scdn.co/image/4faf22545ee65f5781b9b98b8e2d11498a1b00ab",
              "width": 64
            }
          ],
          "name": "Vol. 4 (2009 Remastered Version)",
          "release_date": "1972-09-25",
          "release_date_precision": "day",
          "total_tracks": 10,
          "type": "album",
          "uri": "spotify:album:3iRW4cZOM90lX9Rtc2Qglh"
        },
        "artists": [
          {
            "external_urls": {
              "spotify": "https://open.spotify.com/artist/5M52tdBnJaKSvOpJGz8mfZ"
            },
            "href": "https://api.spotify.com/v1/artists/5M52tdBnJaKSvOpJGz8mfZ",
            "id": "5M52tdBnJaKSvOpJGz8mfZ",
            "name": "Black Sabbath",
            "type": "artist",
            "uri": "spotify:artist:5M52tdBnJaKSvOpJGz8mfZ"
          }
        ],
        "disc_number": 1,
        "duration_ms": 188773,
        "explicit": false,
        "external_ids": {
          "isrc": "GBAJE7200129"
        },
        "external_urls": {
          "spotify": "https://open.spotify.com/track/0ye6hMXikst1lBKp9xVuvg"
        },
        "href": "https://api.spotify.com/v1/tracks/0ye6hMXikst1lBKp9xVuvg",
        "id": "0ye6hMXikst1lBKp9xVuvg",
        "is_local": false,
        "is_playable": true,
        "name": "Tomorrow's Dream - 2009 Remastered Version",
        "popularity": 43,
        "preview_url": "https://p.scdn.co/mp3-preview/3eb7e7ff3d6b9b32e99cce09959fc4d673c34760?cid=d8a5ed958d274c2e8ee717e6a4b0971d",
        "track_number": 2,
        "type": "track",
        "uri": "spotify:track:0ye6hMXikst1lBKp9xVuvg"
      }
    },
    {
      "added_at": "2017-10-30T17:35:39Z",
      "track": {
        "album": {
          "album_type": "album",
          "artists": [
            {
              "external_urls": {
                "spotify": "https://open.spotify.com/artist/5M52tdBnJaKSvOpJGz8mfZ"
              },
              "href": "https://api.spotify.com/v1/artists/5M52tdBnJaKSvOpJGz8mfZ",
              "id": "5M52tdBnJaKSvOpJGz8mfZ",
              "name": "Black Sabbath",
              "type": "artist",
              "uri": "spotify:artist:5M52tdBnJaKSvOpJGz8mfZ"
            }
          ],
          "external_urls": {
            "spotify": "https://open.spotify.com/album/3iRW4cZOM90lX9Rtc2Qglh"
          },
          "href": "https://api.spotify.com/v1/albums/3iRW4cZOM90lX9Rtc2Qglh",
          "id": "3iRW4cZOM90lX9Rtc2Qglh",
          "images": [
            {
              "height": 640,
              "url": "https://i.scdn.co/image/6fece4e967304bcecaac8acf434227c2a7c13e31",
              "width": 640
            },
            {
              "height": 300,
              "url": "https://i.scdn.co/image/5805ee36907961fa1d1e46a2f5653ea892b1b9ad",
              "width": 300
            },
            {
              "height": 64,
              "url": "https://i.scdn.co/image/4faf22545ee65f5781b9b98b8e2d11498a1b00ab",
              "width": 64
            }
          ],
          "name": "Vol. 4 (2009 Remastered Version)",
          "release_date": "1972-09-25",
          "release_date_precision": "day",
          "total_tracks": 10,
          "type": "album",
          "uri": "spotify:album:3iRW4cZOM90lX9Rtc2Qglh"
        },
        "artists": [
          {
            "external_urls": {
              "spotify": "https://open.spotify.com/artist/5M52tdBnJaKSvOpJGz8mfZ"
            },
            "href": "https://api.spotify.com/v1/artists/5M52tdBnJaKSvOpJGz8mfZ",
            "id": "5M52tdBnJaKSvOpJGz8mfZ",
            "name": "Black Sabbath",
            "type": "artist",
            "uri": "spotify:artist:5M52tdBnJaKSvOpJGz8mfZ"
          }
        ],
        "disc_number": 1,
        "duration_ms": 271120,
        "explicit": false,
        "external_ids": {
          "isrc": "GBAJE7200132"
        },
        "external_urls": {
          "spotify": "https://open.spotify.com/track/0qkm99RLAyoLBqWDc4fCF1"
        },
        "href": "https://api.spotify.com/v1/tracks/0qkm99RLAyoLBqWDc4fCF1",
        "id": "0qkm99RLAyoLBqWDc4fCF1",
        "is_local": false,
        "is_playable": true,
        "name": "Supernaut - 2009 Remastered Version",
        "popularity": 48,
        "preview_url": "https://p.scdn.co/mp3-preview/96999e8ae75d065947483616198d7535ae336fa2?cid=d8a5ed958d274c2e8ee717e6a4b0971d",
        "track_number": 5,
        "type": "track",
        "uri": "spotify:track:0qkm99RLAyoLBqWDc4fCF1"
      }
    },
    {
      "added_at": "2017-10-30T17:35:39Z",
      "track": {
        "album": {
          "album_type": "album",
          "artists": [
            {
              "external_urls": {
                "spotify": "https://open.spotify.com/artist/5M52tdBnJaKSvOpJGz8mfZ"
              },
              "href": "https://api.spotify.com/v1/artists/5M52tdBnJaKSvOpJGz8mfZ",
              "id": "5M52tdBnJaKSvOpJGz8mfZ",
              "name": "Black Sabbath",
              "type": "artist",
              "uri": "spotify:artist:5M52tdBnJaKSvOpJGz8mfZ"
            }
          ],
          "external_urls": {
            "spotify": "https://open.spotify.com/album/3iRW4cZOM90lX9Rtc2Qglh"
          },
          "href": "https://api.spotify.com/v1/albums/3iRW4cZOM90lX9Rtc2Qglh",
          "id": "3iRW4cZOM90lX9Rtc2Qglh",
          "images": [
            {
              "height": 640,
              "url": "https://i.scdn.co/image/6fece4e967304bcecaac8acf434227c2a7c13e31",
              "width": 640
            },
            {
              "height": 300,
              "url": "https://i.scdn.co/image/5805ee36907961fa1d1e46a2f5653ea892b1b9ad",
              "width": 300
            },
            {
              "height": 64,
              "url": "https://i.scdn.co/image/4faf22545ee65f5781b9b98b8e2d11498a1b00ab",
              "width": 64
            }
          ],
          "name": "Vol. 4 (2009 Remastered Version)",
          "release_date": "1972-09-25",
          "release_date_precision": "day",
          "total_tracks": 10,
          "type": "album",
          "uri": "spotify:album:3iRW4cZOM90lX9Rtc2Qglh"
        },
        "artists": [
          {
            "external_urls": {
              "spotify": "https://open.spotify.com/artist/5M52tdBnJaKSvOpJGz8mfZ"
            },
            "href": "https://api.spotify.com/v1/artists/5M52tdBnJaKSvOpJGz8mfZ",
            "id": "5M52tdBnJaKSvOpJGz8mfZ",
            "name": "Black Sabbath",
            "type": "artist",
            "uri": "spotify:artist:5M52tdBnJaKSvOpJGz8mfZ"
          }
        ],
        "disc_number": 1,
        "duration_ms": 326333,
        "explicit": false,
        "external_ids": {
          "isrc": "GBAJE7200133"
        },
        "external_urls": {
          "spotify": "https://open.spotify.com/track/5asbJnP2OL9tPGGXX1efu7"
        },
        "href": "https://api.spotify.com/v1/tracks/5asbJnP2OL9tPGGXX1efu7",
        "id": "5asbJnP2OL9tPGGXX1efu7",
        "is_local": false,
        "is_playable": true,
        "name": "Snowblind - 2009 Remastered Version",
        "popularity": 50,
        "preview_url": "https://p.scdn.co/mp3-preview/86e8ea8a8b1d8b1749f69b9164398425ddbbe7ce?cid=d8a5ed958d274c2e8ee717e6a4b0971d",
        "track_number": 6,
        "type": "track",
        "uri": "spotify:track:5asbJnP2OL9tPGGXX1efu7"
      }
    },
    {
      "added_at": "2017-10-30T17:35:39Z",
      "track": {
        "album": {
          "album_type": "album",
          "artists": [
            {
              "external_urls": {
                "spotify": "https://open.spotify.com/artist/5M52tdBnJaKSvOpJGz8mfZ"
              },
              "href": "https://api.spotify.com/v1/artists/5M52tdBnJaKSvOpJGz8mfZ",
              "id": "5M52tdBnJaKSvOpJGz8mfZ",
              "name": "Black Sabbath",
              "type": "artist",
              "uri": "spotify:artist:5M52tdBnJaKSvOpJGz8mfZ"
            }
          ],
          "external_urls": {
            "spotify": "https://open.spotify.com/album/3iRW4cZOM90lX9Rtc2Qglh"
          },
          "href": "https://api.spotify.com/v1/albums/3iRW4cZOM90lX9Rtc2Qglh",
          "id": "3iRW4cZOM90lX9Rtc2Qglh",
          "images": [
            {
              "height": 640,
              "url": "https://i.scdn.co/image/6fece4e967304bcecaac8acf434227c2a7c13e31",
              "width": 640
            },
            {
              "height": 300,
              "url": "https://i.scdn.co/image/5805ee36907961fa1d1e46a2f5653ea892b1b9ad",
              "width": 300
            },
            {
              "height": 64,
              "url": "https://i.scdn.co/image/4faf22545ee65f5781b9b98b8e2d11498a1b00ab",
              "width": 64
            }
          ],
          "name": "Vol. 4 (2009 Remastered Version)",
          "release_date": "1972-09-25",
          "release_date_precision": "day",
          "total_tracks": 10,
          "type": "album",
          "uri": "spotify:album:3iRW4cZOM90lX9Rtc2Qglh"
        },
        "artists": [
          {
            "external_urls": {
              "spotify": "https://open.spotify.com/artist/5M52tdBnJaKSvOpJGz8mfZ"
            },
            "href": "https://api.spotify.com/v1/artists/5M52tdBnJaKSvOpJGz8mfZ",
            "id": "5M52tdBnJaKSvOpJGz8mfZ",
            "name": "Black Sabbath",
            "type": "artist",
            "uri": "spotify:artist:5M52tdBnJaKSvOpJGz8mfZ"
          }
        ],
        "disc_number": 1,
        "duration_ms": 148000,
        "explicit": false,
        "external_ids": {
          "isrc": "GBAJE7200136"
        },
        "external_urls": {
          "spotify": "https://open.spotify.com/track/5sq05BdSho80w7wY5JZtkP"
        },
        "href": "https://api.spotify.com/v1/tracks/5sq05BdSho80w7wY5JZtkP",
        "id": "5sq05BdSho80w7wY5JZtkP",
        "is_local": false,
        "is_playable": true,
        "name": "St. Vitus' Dance - 2009 Remastered Version",
        "popularity": 35,
        "preview_url": "https://p.scdn.co/mp3-preview/6c5c162ad54cab216b092f5807b0f5fec90dfdd9?cid=d8a5ed958d274c2e8ee717e6a4b0971d",
        "track_number": 9,
        "type": "track",
        "uri": "spotify:track:5sq05BdSho80w7wY5JZtkP"
      }
    },
    {
      "added_at": "2017-10-30T17:35:38Z",
      "track": {
        "album": {
          "album_type": "album",
          "artists": [
            {
              "external_urls": {
                "spotify": "https://open.spotify.com/artist/5M52tdBnJaKSvOpJGz8mfZ"
              },
              "href": "https://api.spotify.com/v1/artists/5M52tdBnJaKSvOpJGz8mfZ",
              "id": "5M52tdBnJaKSvOpJGz8mfZ",
              "name": "Black Sabbath",
              "type": "artist",
              "uri": "spotify:artist:5M52tdBnJaKSvOpJGz8mfZ"
            }
          ],
          "external_urls": {
            "spotify": "https://open.spotify.com/album/6vKZWeBFGy7phxXP727tOa"
          },
          "href": "https://api.spotify.com/v1/albums/6vKZWeBFGy7phxXP727tOa",
          "id": "6vKZWeBFGy7phxXP727tOa",
          "images": [
            {
              "height": 640,
              "url": "https://i.scdn.co/image/325a8bbcb634b99b8256a2c9f78f58cb56788b4b",
              "width": 640
            },
            {
              "height": 300,
              "url": "https://i.scdn.co/image/8fc6c6176e8db6a3e74b37bd40c8fc9afdf707df",
              "width": 300
            },
            {
              "height": 64,
              "url": "https://i.scdn.co/image/2ca257fcc4ae466f69e49ecac99d0b3fb1f40817",
              "width": 64
            }
          ],
          "name": "Sabbath Bloody Sabbath (2009 Remastered Version)",
          "release_date": "1973-12-01",
          "release_date_precision": "day",
          "total_tracks": 8,
          "type": "album",
          "uri": "spotify:album:6vKZWeBFGy7phxXP727tOa"
        },
        "artists": [
          {
            "external_urls": {
              "spotify": "https://open.spotify.com/artist/5M52tdBnJaKSvOpJGz8mfZ"
            },
            "href": "https://api.spotify.com/v1/artists/5M52tdBnJaKSvOpJGz8mfZ",
            "id": "5M52tdBnJaKSvOpJGz8mfZ",
            "name": "Black Sabbath",
            "type": "artist",
            "uri": "spotify:artist:5M52tdBnJaKSvOpJGz8mfZ"
          }
        ],
        "disc_number": 1,
        "duration_ms": 375106,
        "explicit": false,
        "external_ids": {
          "isrc": "GBAJE7300023"
        },
        "external_urls": {
          "spotify": "https://open.spotify.com/track/1DCeBMEXMOZr3OEGIbViiV"
        },
        "href": "https://api.spotify.com/v1/tracks/1DCeBMEXMOZr3OEGIbViiV",
        "id": "1DCeBMEXMOZr3OEGIbViiV",
        "is_local": false,
        "is_playable": true,
        "name": "A National Acrobat - 2009 Remastered Version",
        "popularity": 48,
        "preview_url": "https://p.scdn.co/mp3-preview/0837da45303bb38eb9e888c35a784b52f0999e19?cid=d8a5ed958d274c2e8ee717e6a4b0971d",
        "track_number": 2,
        "type": "track",
        "uri": "spotify:track:1DCeBMEXMOZr3OEGIbViiV"
      }
    },
    {
      "added_at": "2017-10-30T17:35:38Z",
      "track": {
        "album": {
          "album_type": "album",
          "artists": [
            {
              "external_urls": {
                "spotify": "https://open.spotify.com/artist/5M52tdBnJaKSvOpJGz8mfZ"
              },
              "href": "https://api.spotify.com/v1/artists/5M52tdBnJaKSvOpJGz8mfZ",
              "id": "5M52tdBnJaKSvOpJGz8mfZ",
              "name": "Black Sabbath",
              "type": "artist",
              "uri": "spotify:artist:5M52tdBnJaKSvOpJGz8mfZ"
            }
          ],
          "external_urls": {
            "spotify": "https://open.spotify.com/album/6vKZWeBFGy7phxXP727tOa"
          },
          "href": "https://api.spotify.com/v1/albums/6vKZWeBFGy7phxXP727tOa",
          "id": "6vKZWeBFGy7phxXP727tOa",
          "images": [
            {
              "height": 640,
              "url": "https://i.scdn.co/image/325a8bbcb634b99b8256a2c9f78f58cb56788b4b",
              "width": 640
            },
            {
              "height": 300,
              "url": "https://i.scdn.co/image/8fc6c6176e8db6a3e74b37bd40c8fc9afdf707df",
              "width": 300
            },
            {
              "height": 64,
              "url": "https://i.scdn.co/image/2ca257fcc4ae466f69e49ecac99d0b3fb1f40817",
              "width": 64
            }
          ],
          "name": "Sabbath Bloody Sabbath (2009 Remastered Version)",
          "release_date": "1973-12-01",
          "release_date_precision": "day",
          "total_tracks": 8,
          "type": "album",
          "uri": "spotify:album:6vKZWeBFGy7phxXP727tOa"
        },
        "artists": [
          {
            "external_urls": {
              "spotify": "https://open.spotify.com/artist/5M52tdBnJaKSvOpJGz8mfZ"
            },
            "href": "https://api.spotify.com/v1/artists/5M52tdBnJaKSvOpJGz8mfZ",
            "id": "5M52tdBnJaKSvOpJGz8mfZ",
            "name": "Black Sabbath",
            "type": "artist",
            "uri": "spotify:artist:5M52tdBnJaKSvOpJGz8mfZ"
          }
        ],
        "disc_number": 1,
        "duration_ms": 342440,
        "explicit": false,
        "external_ids": {
          "isrc": "GBAJE7300026"
        },
        "external_urls": {
          "spotify": "https://open.spotify.com/track/0jbY2C4Ci2VTrWNNLW3AbY"
        },
        "href": "https://api.spotify.com/v1/tracks/0jbY2C4Ci2VTrWNNLW3AbY",
        "id": "0jbY2C4Ci2VTrWNNLW3AbY",
        "is_local": false,
        "is_playable": true,
        "name": "Killing Yourself to Live - 2009 Remastered Version",
        "popularity": 44,
        "preview_url": "https://p.scdn.co/mp3-preview/02bd2ee69b19ada121c58fdd6273f18a582ec11d?cid=d8a5ed958d274c2e8ee717e6a4b0971d",
        "track_number": 5,
        "type": "track",
        "uri": "spotify:track:0jbY2C4Ci2VTrWNNLW3AbY"
      }
    },
    {
      "added_at": "2017-10-30T17:34:54Z",
      "track": {
        "album": {
          "album_type": "album",
          "artists": [
            {
              "external_urls": {
                "spotify": "https://open.spotify.com/artist/5M52tdBnJaKSvOpJGz8mfZ"
              },
              "href": "https://api.spotify.com/v1/artists/5M52tdBnJaKSvOpJGz8mfZ",
              "id": "5M52tdBnJaKSvOpJGz8mfZ",
              "name": "Black Sabbath",
              "type": "artist",
              "uri": "spotify:artist:5M52tdBnJaKSvOpJGz8mfZ"
            }
          ],
          "external_urls": {
            "spotify": "https://open.spotify.com/album/5WXL9YjbNd4GIqWc9mZOOq"
          },
          "href": "https://api.spotify.com/v1/albums/5WXL9YjbNd4GIqWc9mZOOq",
          "id": "5WXL9YjbNd4GIqWc9mZOOq",
          "images": [
            {
              "height": 640,
              "url": "https://i.scdn.co/image/be49138ca73e7c92a39b22cd51a59ba17104e1eb",
              "width": 640
            },
            {
              "height": 300,
              "url": "https://i.scdn.co/image/a98e4463f108b4fe568aee7881f5496bcd1a48b5",
              "width": 300
            },
            {
              "height": 64,
              "url": "https://i.scdn.co/image/96c2c752d5a8bd83a8953374e3616f9f78454af5",
              "width": 64
            }
          ],
          "name": "13",
          "release_date": "2013-01-01",
          "release_date_precision": "day",
          "total_tracks": 12,
          "type": "album",
          "uri": "spotify:album:5WXL9YjbNd4GIqWc9mZOOq"
        },
        "artists": [
          {
            "external_urls": {
              "spotify": "https://open.spotify.com/artist/5M52tdBnJaKSvOpJGz8mfZ"
            },
            "href": "https://api.spotify.com/v1/artists/5M52tdBnJaKSvOpJGz8mfZ",
            "id": "5M52tdBnJaKSvOpJGz8mfZ",
            "name": "Black Sabbath",
            "type": "artist",
            "uri": "spotify:artist:5M52tdBnJaKSvOpJGz8mfZ"
          }
        ],
        "disc_number": 1,
        "duration_ms": 299933,
        "explicit": false,
        "external_ids": {
          "isrc": "GBUM71302422"
        },
        "external_urls": {
          "spotify": "https://open.spotify.com/track/1PZ3DwxBYzuRYXt2fpomfY"
        },
        "href": "https://api.spotify.com/v1/tracks/1PZ3DwxBYzuRYXt2fpomfY",
        "id": "1PZ3DwxBYzuRYXt2fpomfY",
        "is_local": false,
        "is_playable": true,
        "linked_from": {
          "external_urls": {
            "spotify": "https://open.spotify.com/track/6PPs4wEwrTQrVTNypvHa3L"
          },
          "href": "https://api.spotify.com/v1/tracks/6PPs4wEwrTQrVTNypvHa3L",
          "id": "6PPs4wEwrTQrVTNypvHa3L",
          "type": "track",
          "uri": "spotify:track:6PPs4wEwrTQrVTNypvHa3L"
        },
        "name": "Loner",
        "popularity": 51,
        "preview_url": "https://p.scdn.co/mp3-preview/f13be60bf9bfcdf09142c3eb7289a48bf85d33a9?cid=d8a5ed958d274c2e8ee717e6a4b0971d",
        "track_number": 3,
        "type": "track",
        "uri": "spotify:track:1PZ3DwxBYzuRYXt2fpomfY"
      }
    },
    {
      "added_at": "2017-10-30T17:34:54Z",
      "track": {
        "album": {
          "album_type": "album",
          "artists": [
            {
              "external_urls": {
                "spotify": "https://open.spotify.com/artist/5M52tdBnJaKSvOpJGz8mfZ"
              },
              "href": "https://api.spotify.com/v1/artists/5M52tdBnJaKSvOpJGz8mfZ",
              "id": "5M52tdBnJaKSvOpJGz8mfZ",
              "name": "Black Sabbath",
              "type": "artist",
              "uri": "spotify:artist:5M52tdBnJaKSvOpJGz8mfZ"
            }
          ],
          "external_urls": {
            "spotify": "https://open.spotify.com/album/5WXL9YjbNd4GIqWc9mZOOq"
          },
          "href": "https://api.spotify.com/v1/albums/5WXL9YjbNd4GIqWc9mZOOq",
          "id": "5WXL9YjbNd4GIqWc9mZOOq",
          "images": [
            {
              "height": 640,
              "url": "https://i.scdn.co/image/be49138ca73e7c92a39b22cd51a59ba17104e1eb",
              "width": 640
            },
            {
              "height": 300,
              "url": "https://i.scdn.co/image/a98e4463f108b4fe568aee7881f5496bcd1a48b5",
              "width": 300
            },
            {
              "height": 64,
              "url": "https://i.scdn.co/image/96c2c752d5a8bd83a8953374e3616f9f78454af5",
              "width": 64
            }
          ],
          "name": "13",
          "release_date": "2013-01-01",
          "release_date_precision": "day",
          "total_tracks": 12,
          "type": "album",
          "uri": "spotify:album:5WXL9YjbNd4GIqWc9mZOOq"
        },
        "artists": [
          {
            "external_urls": {
              "spotify": "https://open.spotify.com/artist/5M52tdBnJaKSvOpJGz8mfZ"
            },
            "href": "https://api.spotify.com/v1/artists/5M52tdBnJaKSvOpJGz8mfZ",
            "id": "5M52tdBnJaKSvOpJGz8mfZ",
            "name": "Black Sabbath",
            "type": "artist",
            "uri": "spotify:artist:5M52tdBnJaKSvOpJGz8mfZ"
          }
        ],
        "disc_number": 1,
        "duration_ms": 277786,
        "explicit": false,
        "external_ids": {
          "isrc": "GBUM71302423"
        },
        "external_urls": {
          "spotify": "https://open.spotify.com/track/4HFRItYjNrcwT6Vbtbk2i4"
        },
        "href": "https://api.spotify.com/v1/tracks/4HFRItYjNrcwT6Vbtbk2i4",
        "id": "4HFRItYjNrcwT6Vbtbk2i4",
        "is_local": false,
        "is_playable": true,
        "linked_from": {
          "external_urls": {
            "spotify": "https://open.spotify.com/track/1GZh5L0QotO3R7nrFQPEsK"
          },
          "href": "https://api.spotify.com/v1/tracks/1GZh5L0QotO3R7nrFQPEsK",
          "id": "1GZh5L0QotO3R7nrFQPEsK",
          "type": "track",
          "uri": "spotify:track:1GZh5L0QotO3R7nrFQPEsK"
        },
        "name": "Zeitgeist",
        "popularity": 48,
        "preview_url": "https://p.scdn.co/mp3-preview/0dc91b0706f641dcba53adcc9f7ccd981e8f2fa4?cid=d8a5ed958d274c2e8ee717e6a4b0971d",
        "track_number": 4,
        "type": "track",
        "uri": "spotify:track:4HFRItYjNrcwT6Vbtbk2i4"
      }
    },
    {
      "added_at": "2017-10-30T17:34:54Z",
      "track": {
        "album": {
          "album_type": "album",
          "artists": [
            {
              "external_urls": {
                "spotify": "https://open.spotify.com/artist/5M52tdBnJaKSvOpJGz8mfZ"
              },
              "href": "https://api.spotify.com/v1/artists/5M52tdBnJaKSvOpJGz8mfZ",
              "id": "5M52tdBnJaKSvOpJGz8mfZ",
              "name": "Black Sabbath",
              "type": "artist",
              "uri": "spotify:artist:5M52tdBnJaKSvOpJGz8mfZ"
            }
          ],
          "external_urls": {
            "spotify": "https://open.spotify.com/album/5WXL9YjbNd4GIqWc9mZOOq"
          },
          "href": "https://api.spotify.com/v1/albums/5WXL9YjbNd4GIqWc9mZOOq",
          "id": "5WXL9YjbNd4GIqWc9mZOOq",
          "images": [
            {
              "height": 640,
              "url": "https://i.scdn.co/image/be49138ca73e7c92a39b22cd51a59ba17104e1eb",
              "width": 640
            },
            {
              "height": 300,
              "url": "https://i.scdn.co/image/a98e4463f108b4fe568aee7881f5496bcd1a48b5",
              "width": 300
            },
            {
              "height": 64,
              "url": "https://i.scdn.co/image/96c2c752d5a8bd83a8953374e3616f9f78454af5",
              "width": 64
            }
          ],
          "name": "13",
          "release_date": "2013-01-01",
          "release_date_precision": "day",
          "total_tracks": 12,
          "type": "album",
          "uri": "spotify:album:5WXL9YjbNd4GIqWc9mZOOq"
        },
        "artists": [
          {
            "external_urls": {
              "spotify": "https://open.spotify.com/artist/5M52tdBnJaKSvOpJGz8mfZ"
            },
            "href": "https://api.spotify.com/v1/artists/5M52tdBnJaKSvOpJGz8mfZ",
            "id": "5M52tdBnJaKSvOpJGz8mfZ",
            "name": "Black Sabbath",
            "type": "artist",
            "uri": "spotify:artist:5M52tdBnJaKSvOpJGz8mfZ"
          }
        ],
        "disc_number": 1,
        "duration_ms": 471666,
        "explicit": false,
        "external_ids": {
          "isrc": "GBUM71302418"
        },
        "external_urls": {
          "spotify": "https://open.spotify.com/track/3gY381aWseWtDcnanY9n6u"
        },
        "href": "https://api.spotify.com/v1/tracks/3gY381aWseWtDcnanY9n6u",
        "id": "3gY381aWseWtDcnanY9n6u",
        "is_local": false,
        "is_playable": true,
        "linked_from": {
          "external_urls": {
            "spotify": "https://open.spotify.com/track/6frv1eR78o96PTm4QByjKQ"
          },
          "href": "https://api.spotify.com/v1/tracks/6frv1eR78o96PTm4QByjKQ",
          "id": "6frv1eR78o96PTm4QByjKQ",
          "type": "track",
          "uri": "spotify:track:6frv1eR78o96PTm4QByjKQ"
        },
        "name": "Damaged Soul",
        "popularity": 42,
        "preview_url": "https://p.scdn.co/mp3-preview/481904b14dc156a54d56b26440036457e80b82da?cid=d8a5ed958d274c2e8ee717e6a4b0971d",
        "track_number": 7,
        "type": "track",
        "uri": "spotify:track:3gY381aWseWtDcnanY9n6u"
      }
    },
    {
      "added_at": "2017-10-30T17:34:54Z",
      "track": {
        "album": {
          "album_type": "album",
          "artists": [
            {
              "external_urls": {
                "spotify": "https://open.spotify.com/artist/5M52tdBnJaKSvOpJGz8mfZ"
              },
              "href": "https://api.spotify.com/v1/artists/5M52tdBnJaKSvOpJGz8mfZ",
              "id": "5M52tdBnJaKSvOpJGz8mfZ",
              "name": "Black Sabbath",
              "type": "artist",
              "uri": "spotify:artist:5M52tdBnJaKSvOpJGz8mfZ"
            }
          ],
          "external_urls": {
            "spotify": "https://open.spotify.com/album/5WXL9YjbNd4GIqWc9mZOOq"
          },
          "href": "https://api.spotify.com/v1/albums/5WXL9YjbNd4GIqWc9mZOOq",
          "id": "5WXL9YjbNd4GIqWc9mZOOq",
          "images": [
            {
              "height": 640,
              "url": "https://i.scdn.co/image/be49138ca73e7c92a39b22cd51a59ba17104e1eb",
              "width": 640
            },
            {
              "height": 300,
              "url": "https://i.scdn.co/image/a98e4463f108b4fe568aee7881f5496bcd1a48b5",
              "width": 300
            },
            {
              "height": 64,
              "url": "https://i.scdn.co/image/96c2c752d5a8bd83a8953374e3616f9f78454af5",
              "width": 64
            }
          ],
          "name": "13",
          "release_date": "2013-01-01",
          "release_date_precision": "day",
          "total_tracks": 12,
          "type": "album",
          "uri": "spotify:album:5WXL9YjbNd4GIqWc9mZOOq"
        },
        "artists": [
          {
            "external_urls": {
              "spotify": "https://open.spotify.com/artist/5M52tdBnJaKSvOpJGz8mfZ"
            },
            "href": "https://api.spotify.com/v1/artists/5M52tdBnJaKSvOpJGz8mfZ",
            "id": "5M52tdBnJaKSvOpJGz8mfZ",
            "name": "Black Sabbath",
            "type": "artist",
            "uri": "spotify:artist:5M52tdBnJaKSvOpJGz8mfZ"
          }
        ],
        "disc_number": 1,
        "duration_ms": 358213,
        "explicit": false,
        "external_ids": {
          "isrc": "GBUM71302502"
        },
        "external_urls": {
          "spotify": "https://open.spotify.com/track/0Gnx4WTUEUxA6WBETrp3yJ"
        },
        "href": "https://api.spotify.com/v1/tracks/0Gnx4WTUEUxA6WBETrp3yJ",
        "id": "0Gnx4WTUEUxA6WBETrp3yJ",
        "is_local": false,
        "is_playable": true,
        "linked_from": {
          "external_urls": {
            "spotify": "https://open.spotify.com/track/2PaC2hzwJjYBEdvI023uus"
          },
          "href": "https://api.spotify.com/v1/tracks/2PaC2hzwJjYBEdvI023uus",
          "id": "2PaC2hzwJjYBEdvI023uus",
          "type": "track",
          "uri": "spotify:track:2PaC2hzwJjYBEdvI023uus"
        },
        "name": "Methademic",
        "popularity": 39,
        "preview_url": "https://p.scdn.co/mp3-preview/767436a09146f83ec8909768333073bb6f18844d?cid=d8a5ed958d274c2e8ee717e6a4b0971d",
        "track_number": 9,
        "type": "track",
        "uri": "spotify:track:0Gnx4WTUEUxA6WBETrp3yJ"
      }
    },
    {
      "added_at": "2017-10-25T12:51:47Z",
      "track": {
        "album": {
          "album_type": "album",
          "artists": [
            {
              "external_urls": {
                "spotify": "https://open.spotify.com/artist/2AsusXITU8P25dlRNhcAbG"
              },
              "href": "https://api.spotify.com/v1/artists/2AsusXITU8P25dlRNhcAbG",
              "id": "2AsusXITU8P25dlRNhcAbG",
              "name": "Gotye",
              "type": "artist",
              "uri": "spotify:artist:2AsusXITU8P25dlRNhcAbG"
            }
          ],
          "external_urls": {
            "spotify": "https://open.spotify.com/album/4G2rJNhsKOE6iHgtUqZ0Ye"
          },
          "href": "https://api.spotify.com/v1/albums/4G2rJNhsKOE6iHgtUqZ0Ye",
          "id": "4G2rJNhsKOE6iHgtUqZ0Ye",
          "images": [
            {
              "height": 640,
              "url": "https://i.scdn.co/image/487b8927d712c53c5319eb7e0b30d84dd3c73863",
              "width": 640
            },
            {
              "height": 300,
              "url": "https://i.scdn.co/image/02acedde17be31789a10c931b53a5a957f1a4b0a",
              "width": 300
            },
            {
              "height": 64,
              "url": "https://i.scdn.co/image/c5e863ce1b89bdba5afbb34d90db49130912926d",
              "width": 64
            }
          ],
          "name": "Making Mirrors",
          "release_date": "2011-01-01",
          "release_date_precision": "day",
          "total_tracks": 12,
          "type": "album",
          "uri": "spotify:album:4G2rJNhsKOE6iHgtUqZ0Ye"
        },
        "artists": [
          {
            "external_urls": {
              "spotify": "https://open.spotify.com/artist/2AsusXITU8P25dlRNhcAbG"
            },
            "href": "https://api.spotify.com/v1/artists/2AsusXITU8P25dlRNhcAbG",
            "id": "2AsusXITU8P25dlRNhcAbG",
            "name": "Gotye",
            "type": "artist",
            "uri": "spotify:artist:2AsusXITU8P25dlRNhcAbG"
          },
          {
            "external_urls": {
              "spotify": "https://open.spotify.com/artist/6hk7Yq1DU9QcCCrz9uc0Ti"
            },
            "href": "https://api.spotify.com/v1/artists/6hk7Yq1DU9QcCCrz9uc0Ti",
            "id": "6hk7Yq1DU9QcCCrz9uc0Ti",
            "name": "Kimbra",
            "type": "artist",
            "uri": "spotify:artist:6hk7Yq1DU9QcCCrz9uc0Ti"
          }
        ],
        "disc_number": 1,
        "duration_ms": 244884,
        "explicit": false,
        "external_ids": {
          "isrc": "AUZS21100040"
        },
        "external_urls": {
          "spotify": "https://open.spotify.com/track/1qDrWA6lyx8cLECdZE7TV7"
        },
        "href": "https://api.spotify.com/v1/tracks/1qDrWA6lyx8cLECdZE7TV7",
        "id": "1qDrWA6lyx8cLECdZE7TV7",
        "is_local": false,
        "is_playable": true,
        "name": "Somebody That I Used To Know",
        "popularity": 75,
        "preview_url": "https://p.scdn.co/mp3-preview/8958baf5d6022f3c2cb969ee14bd7d0f98de9a41?cid=d8a5ed958d274c2e8ee717e6a4b0971d",
        "track_number": 3,
        "type": "track",
        "uri": "spotify:track:1qDrWA6lyx8cLECdZE7TV7"
      }
    },
    {
      "added_at": "2017-10-24T14:15:09Z",
      "track": {
        "album": {
          "album_type": "album",
          "artists": [
            {
              "external_urls": {
                "spotify": "https://open.spotify.com/artist/5M52tdBnJaKSvOpJGz8mfZ"
              },
              "href": "https://api.spotify.com/v1/artists/5M52tdBnJaKSvOpJGz8mfZ",
              "id": "5M52tdBnJaKSvOpJGz8mfZ",
              "name": "Black Sabbath",
              "type": "artist",
              "uri": "spotify:artist:5M52tdBnJaKSvOpJGz8mfZ"
            }
          ],
          "external_urls": {
            "spotify": "https://open.spotify.com/album/6KSQLHjRof63DtaUu55SMm"
          },
          "href": "https://api.spotify.com/v1/albums/6KSQLHjRof63DtaUu55SMm",
          "id": "6KSQLHjRof63DtaUu55SMm",
          "images": [
            {
              "height": 640,
              "url": "https://i.scdn.co/image/9186c065e68d24c256fe6ce96789a719739c0854",
              "width": 640
            },
            {
              "height": 300,
              "url": "https://i.scdn.co/image/3ef60cce1aaa4e10b261d2bac09c13bd616d6f69",
              "width": 300
            },
            {
              "height": 64,
              "url": "https://i.scdn.co/image/9da88c397820e54fe6f92fb716d5d59f9da603a7",
              "width": 64
            }
          ],
          "name": "Technical Ecstasy (2009 Remastered Version)",
          "release_date": "1976-09-25",
          "release_date_precision": "day",
          "total_tracks": 8,
          "type": "album",
          "uri": "spotify:album:6KSQLHjRof63DtaUu55SMm"
        },
        "artists": [
          {
            "external_urls": {
              "spotify": "https://open.spotify.com/artist/5M52tdBnJaKSvOpJGz8mfZ"
            },
            "href": "https://api.spotify.com/v1/artists/5M52tdBnJaKSvOpJGz8mfZ",
            "id": "5M52tdBnJaKSvOpJGz8mfZ",
            "name": "Black Sabbath",
            "type": "artist",
            "uri": "spotify:artist:5M52tdBnJaKSvOpJGz8mfZ"
          }
        ],
        "disc_number": 1,
        "duration_ms": 398253,
        "explicit": false,
        "external_ids": {
          "isrc": "GBAJE7600025"
        },
        "external_urls": {
          "spotify": "https://open.spotify.com/track/1oiyxIAxskMgJTIGbNdi3C"
        },
        "href": "https://api.spotify.com/v1/tracks/1oiyxIAxskMgJTIGbNdi3C",
        "id": "1oiyxIAxskMgJTIGbNdi3C",
        "is_local": false,
        "is_playable": true,
        "name": "You Won't Change Me - 2009 Remastered Version",
        "popularity": 31,
        "preview_url": "https://p.scdn.co/mp3-preview/b892d05ad892358453e90bf810c86d451766ec3d?cid=d8a5ed958d274c2e8ee717e6a4b0971d",
        "track_number": 2,
        "type": "track",
        "uri": "spotify:track:1oiyxIAxskMgJTIGbNdi3C"
      }
    },
    {
      "added_at": "2017-10-24T14:15:09Z",
      "track": {
        "album": {
          "album_type": "album",
          "artists": [
            {
              "external_urls": {
                "spotify": "https://open.spotify.com/artist/5M52tdBnJaKSvOpJGz8mfZ"
              },
              "href": "https://api.spotify.com/v1/artists/5M52tdBnJaKSvOpJGz8mfZ",
              "id": "5M52tdBnJaKSvOpJGz8mfZ",
              "name": "Black Sabbath",
              "type": "artist",
              "uri": "spotify:artist:5M52tdBnJaKSvOpJGz8mfZ"
            }
          ],
          "external_urls": {
            "spotify": "https://open.spotify.com/album/6KSQLHjRof63DtaUu55SMm"
          },
          "href": "https://api.spotify.com/v1/albums/6KSQLHjRof63DtaUu55SMm",
          "id": "6KSQLHjRof63DtaUu55SMm",
          "images": [
            {
              "height": 640,
              "url": "https://i.scdn.co/image/9186c065e68d24c256fe6ce96789a719739c0854",
              "width": 640
            },
            {
              "height": 300,
              "url": "https://i.scdn.co/image/3ef60cce1aaa4e10b261d2bac09c13bd616d6f69",
              "width": 300
            },
            {
              "height": 64,
              "url": "https://i.scdn.co/image/9da88c397820e54fe6f92fb716d5d59f9da603a7",
              "width": 64
            }
          ],
          "name": "Technical Ecstasy (2009 Remastered Version)",
          "release_date": "1976-09-25",
          "release_date_precision": "day",
          "total_tracks": 8,
          "type": "album",
          "uri": "spotify:album:6KSQLHjRof63DtaUu55SMm"
        },
        "artists": [
          {
            "external_urls": {
              "spotify": "https://open.spotify.com/artist/5M52tdBnJaKSvOpJGz8mfZ"
            },
            "href": "https://api.spotify.com/v1/artists/5M52tdBnJaKSvOpJGz8mfZ",
            "id": "5M52tdBnJaKSvOpJGz8mfZ",
            "name": "Black Sabbath",
            "type": "artist",
            "uri": "spotify:artist:5M52tdBnJaKSvOpJGz8mfZ"
          }
        ],
        "disc_number": 1,
        "duration_ms": 428520,
        "explicit": false,
        "external_ids": {
          "isrc": "GBAJE7600031"
        },
        "external_urls": {
          "spotify": "https://open.spotify.com/track/1mLQNcCNIUGj4A8BukuTkz"
        },
        "href": "https://api.spotify.com/v1/tracks/1mLQNcCNIUGj4A8BukuTkz",
        "id": "1mLQNcCNIUGj4A8BukuTkz",
        "is_local": false,
        "is_playable": true,
        "name": "Dirty Women - 2009 Remastered Version",
        "popularity": 34,
        "preview_url": "https://p.scdn.co/mp3-preview/d98f41633b6e14c0d46ee280c602c5aaefc7b884?cid=d8a5ed958d274c2e8ee717e6a4b0971d",
        "track_number": 8,
        "type": "track",
        "uri": "spotify:track:1mLQNcCNIUGj4A8BukuTkz"
      }
    }
  ],
  "limit": 50,
  "next": null,
  "offset": 650,
  "previous": "https://api.spotify.com/v1/me/tracks?offset=600&limit=50&market=from_token",
  "total": 663
}